deepdialog/__init__.py
deepdialog/logger.py
deepdialog/version.txt
deepdialog/common/__init__.py
deepdialog/common/build_dialog_train_data.py
deepdialog/common/component.py
deepdialog/common/dialog_state.py
deepdialog/common/make_init_state.py
deepdialog/common/parse_story.py
deepdialog/common/system_action.py
deepdialog/common/user_action.py
deepdialog/dpl/__init__.py
deepdialog/dpl/dpl.py
deepdialog/dpl/keras_dpl.py
deepdialog/dst/__init__.py
deepdialog/dst/dst.py
deepdialog/dst/keras_dst.py
deepdialog/faq/__init__.py
deepdialog/faq/faq.py
deepdialog/nlg/__init__.py
deepdialog/nlg/ext_sysact.py
deepdialog/nlg/nlg.py
deepdialog/nlu/__init__.py
deepdialog/nlu/crf_slot_filler.py
deepdialog/nlu/data_to_iob.py
deepdialog/nlu/keras_crf.py
deepdialog/nlu/keras_intent.py
deepdialog/nlu/keras_ner.py
deepdialog/nlu/load_nlu_data.py
deepdialog/nlu/nlu.py
deepdialog/nlu/slot_filler.py
deepdialog/nlu/test.py
deepdialog/serve/__init__.py
deepdialog/serve/__main__.py
deepdialog/serve/serve.py
deepdialog/train/__init__.py
deepdialog/train/__main__.py
deepdialog/train/dpl.py
deepdialog/train/dst.py
deepdialog/train/nlg.py
deepdialog/train/nlu.py
deepdialog-0.1.4.dist-info/METADATA
deepdialog-0.1.4.dist-info/WHEEL
deepdialog-0.1.4.dist-info/top_level.txt
deepdialog-0.1.4.dist-info/RECORD
